neuracore_types/__init__.py
neuracore_types/batched_nc_data/__init__.py
neuracore_types/batched_nc_data/batched_camera_data.py
neuracore_types/batched_nc_data/batched_custom_1d_data.py
neuracore_types/batched_nc_data/batched_end_effector_pose_data.py
neuracore_types/batched_nc_data/batched_joint_data.py
neuracore_types/batched_nc_data/batched_language_data.py
neuracore_types/batched_nc_data/batched_nc_data.py
neuracore_types/batched_nc_data/batched_parallel_gripper_open_amount_data.py
neuracore_types/batched_nc_data/batched_point_cloud_data.py
neuracore_types/batched_nc_data/batched_pose_data.py
neuracore_types/dataset/__init__.py
neuracore_types/dataset/dataset.py
neuracore_types/endpoints/__init__.py
neuracore_types/endpoints/endpoint_requests.py
neuracore_types/episode/__init__.py
neuracore_types/episode/episode.py
neuracore_types/importer/__init__.py
neuracore_types/importer/config.py
neuracore_types/importer/data_config.py
neuracore_types/importer/transform.py
neuracore_types/nc_data/__init__.py
neuracore_types/nc_data/camera_data.py
neuracore_types/nc_data/custom_1d_data.py
neuracore_types/nc_data/end_effector_pose_data.py
neuracore_types/nc_data/joint_data.py
neuracore_types/nc_data/language_data.py
neuracore_types/nc_data/nc_data.py
neuracore_types/nc_data/parallel_gripper_open_amount_data.py
neuracore_types/nc_data/point_cloud_data.py
neuracore_types/nc_data/pose_data.py
neuracore_types/synchronization/__init__.py
neuracore_types/synchronization/synchronization.py
neuracore_types/synchronization/synchronization_requests.py
neuracore_types/training/__init__.py
neuracore_types/training/training.py
neuracore_types/training/training_requests.py
neuracore_types/upload/__init__.py
neuracore_types/upload/upload.py
neuracore_types/utils/__init__.py
neuracore_types/utils/depth_utils.py
neuracore_types/utils/name_utils.py
neuracore_types/utils/pydantic_to_ts.py
neuracore_types-6.1.0.dist-info/METADATA
neuracore_types-6.1.0.dist-info/WHEEL
neuracore_types-6.1.0.dist-info/licenses/LICENSE
neuracore_types-6.1.0.dist-info/RECORD
