Metadata-Version: 2.4
Name: neuracore-types
Version: 6.1.0
Summary: Shared type definitions for Neuracore.
Author: Neuracore
License: MIT
License-File: LICENSE
Requires-Python: >=3.9
Requires-Dist: grpcio-tools
Requires-Dist: names-generator
Requires-Dist: numpy>=2.0.0
Requires-Dist: ordered-set
Requires-Dist: pillow
Requires-Dist: pydantic-to-typescript2>=1.0.0
Requires-Dist: pydantic>=2.0.0
Requires-Dist: scipy
Provides-Extra: dev
Requires-Dist: pre-commit; extra == 'dev'
Requires-Dist: pytest; extra == 'dev'
Provides-Extra: ml
Requires-Dist: huggingface-hub; extra == 'ml'
Requires-Dist: torch; extra == 'ml'
Requires-Dist: transformers; extra == 'ml'
